{"cameraMode":{"drawMode":0,"name":"Shaded","section":"Shading Mode"},"sceneLighting":true,"audioPlay":false,"sceneViewState":{"showFog":true,"showMaterialUpdate":false,"showSkybox":true,"showFlares":true,"showImageEffects":true,"showParticleSystems":true},"in2DMode":false,"pivot":{"x":5.280156400999658e-8,"y":0.5191766023635864,"z":0.017885226756334306},"rotation":{"x":0.030674606561660768,"y":0.8896088004112244,"z":-0.060417041182518008,"w":0.4516691565513611},"size":1.714299201965332,"orthographic":false}